{
  "quotes": [
    {
      "category": "Success",
      "list": [
        {
          "quote": "Success is not final, failure is not fatal: It is the courage to continue that counts.",
          "author": "Winston Churchill"
        },
        {
          "quote": "Success usually comes to those who are too busy to be looking for it.",
          "author": "Henry David Thoreau"
        },
        {
          "quote": "The road to success and the road to failure are almost exactly the same.",
          "author": "Colin R. Davis"
        },
        {
          "quote": "Success is not the key to happiness. Happiness is the key to success.",
          "author": "Albert Schweitzer"
        },
        {
          "quote": "Success is not in what you have, but who you are.",
          "author": "Bo Bennett"
        },
        {
          "quote": "The difference between a successful person and others is not a lack of strength, not a lack of knowledge, but rather a lack of will.",
          "author": "Vince Lombardi"
        },
        {
          "quote": "Success is not just about making money. It's about making a difference.",
          "author": "Unknown"
        },
        {
          "quote": "The only place where success comes before work is in the dictionary.",
          "author": "Vidal Sassoon"
        },
        {
          "quote": "Success is not measured by what you accomplish, but by the opposition you have encountered, and the courage with which you have maintained the struggle against overwhelming odds.",
          "author": "Orison Swett Marden"
        },
        {
          "quote": "Success is not the absence of failure; it's the persistence through failure.",
          "author": "Aisha Tyler"
        },
        {
          "quote": "The secret of success is to know something nobody else knows.",
          "author": "Aristotle Onassis"
        },
        {
          "quote": "Success is not for the chosen few, but for the few who choose it.",
          "author": "Unknown"
        },
        {
          "quote": "Success is not a destination, but the road that you're on. Being successful means that you're working hard and walking your walk every day. You can only live your dream by working hard towards it. That's living your dream.",
          "author": "Marlon Wayans"
        },
        {
          "quote": "Success is not the key to success. Persistence and determination alone are omnipotent.",
          "author": "Ray Kroc"
        },
        {
          "quote": "The greatest glory in living lies not in never falling, but in rising every time we fall.",
          "author": "Nelson Mandela"
        },
        {
          "quote": "Success is not about the destination, it's about the journey.",
          "author": "Zig Ziglar"
        },
        {
          "quote": "Success is the sum of small efforts, repeated day in and day out.",
          "author": "Robert Collier"
        },
        {
          "quote": "Success is not how high you have climbed, but how you make a positive difference to the world.",
          "author": "Roy T. Bennett"
        },
        {
          "quote": "Success is not just about making money. It's about making a difference.",
          "author": "Unknown"
        },
        {
          "quote": "Success is not final, failure is not fatal: It is the courage to continue that counts.",
          "author": "Winston Churchill"
        }
      ]
    },
    {
      "category": "Inspirational",
      "list": [
        {
          "quote": "The only way to do great work is to love what you do.",
          "author": "Steve Jobs"
        },
        {
          "quote": "Your time is limited, don't waste it living someone else's life.",
          "author": "Steve Jobs"
        },
        {
          "quote": "Believe you can and you're halfway there.",
          "author": "Theodore Roosevelt"
        },
        {
          "quote": "Don't watch the clock; do what it does. Keep going.",
          "author": "Sam Levenson"
        },
        {
          "quote": "The future belongs to those who believe in the beauty of their dreams.",
          "author": "Eleanor Roosevelt"
        },
        {
          "quote": "The only limit to our realization of tomorrow will be our doubts of today.",
          "author": "Franklin D. Roosevelt"
        },
        {
          "quote": "The harder I work, the luckier I get.",
          "author": "Gary Player"
        },
        {
          "quote": "The only way to predict the future is to create it.",
          "author": "Peter Drucker"
        },
        {
          "quote": "The best way to predict your future is to create it.",
          "author": "Abraham Lincoln"
        },
        {
          "quote": "Success is not final, failure is not fatal: It is the courage to continue that counts.",
          "author": "Winston Churchill"
        },
        {
          "quote": "Success usually comes to those who are too busy to be looking for it.",
          "author": "Henry David Thoreau"
        },
        {
          "quote": "The only way to do great work is to love what you do.",
          "author": "Steve Jobs"
        },
        {
          "quote": "Your time is limited, don't waste it living someone else's life.",
          "author": "Steve Jobs"
        },
        {
          "quote": "Believe you can and you're halfway there.",
          "author": "Theodore Roosevelt"
        },
        {
          "quote": "Don't watch the clock; do what it does. Keep going.",
          "author": "Sam Levenson"
        },
        {
          "quote": "The future belongs to those who believe in the beauty of their dreams.",
          "author": "Eleanor Roosevelt"
        },
        {
          "quote": "The only limit to our realization of tomorrow will be our doubts of today.",
          "author": "Franklin D. Roosevelt"
        },
        {
          "quote": "The harder I work, the luckier I get.",
          "author": "Gary Player"
        },
        {
          "quote": "The only way to predict the future is to create it.",
          "author": "Peter Drucker"
        },
        {
          "quote": "The best way to predict your future is to create it.",
          "author": "Abraham Lincoln"
        }
      ]
    },
    {
      "category": "Positivity",
      "list": [
        {
          "quote": "The positive thinker sees the invisible, feels the intangible, and achieves the impossible.",
          "author": "Winston Churchill"
        },
        {
          "quote": "In every day, there are 1,440 minutes. That means we have 1,440 daily opportunities to make a positive impact.",
          "author": "Les Brown"
        },
        {
          "quote": "Positivity always wins…Always.",
          "author": "Gary Vaynerchuk"
        },
        {
          "quote": "Believe you can and you're halfway there.",
          "author": "Theodore Roosevelt"
        },
        {
          "quote": "The positive thinker sees the invisible, feels the intangible, and achieves the impossible.",
          "author": "Winston Churchill"
        },
        {
          "quote": "In every day, there are 1,440 minutes. That means we have 1,440 daily opportunities to make a positive impact.",
          "author": "Les Brown"
        },
        {
          "quote": "Positivity always wins…Always.",
          "author": "Gary Vaynerchuk"
        },
        {
          "quote": "Believe you can and you're halfway there.",
          "author": "Theodore Roosevelt"
        },
        {
          "quote": "The positive thinker sees the invisible, feels the intangible, and achieves the impossible.",
          "author": "Winston Churchill"
        },
        {
          "quote": "In every day, there are 1,440 minutes. That means we have 1,440 daily opportunities to make a positive impact.",
          "author": "Les Brown"
        },
        {
          "quote": "Positivity always wins…Always.",
          "author": "Gary Vaynerchuk"
        },
        {
          "quote": "Believe you can and you're halfway there.",
          "author": "Theodore Roosevelt"
        },
        {
          "quote": "The positive thinker sees the invisible, feels the intangible, and achieves the impossible.",
          "author": "Winston Churchill"
        },
        {
          "quote": "In every day, there are 1,440 minutes. That means we have 1,440 daily opportunities to make a positive impact.",
          "author": "Les Brown"
        },
        {
          "quote": "Positivity always wins…Always.",
          "author": "Gary Vaynerchuk"
        },
        {
          "quote": "Believe you can and you're halfway there.",
          "author": "Theodore Roosevelt"
        },
        {
          "quote": "The positive thinker sees the invisible, feels the intangible, and achieves the impossible.",
          "author": "Winston Churchill"
        },
        {
          "quote": "In every day, there are 1,440 minutes. That means we have 1,440 daily opportunities to make a positive impact.",
          "author": "Les Brown"
        },
        {
          "quote": "Positivity always wins…Always.",
          "author": "Gary Vaynerchuk"
        },
        {
          "quote": "Believe you can and you're halfway there.",
          "author": "Theodore Roosevelt"
        }
      ]
    },
    {
      "category": "Perseverance",
      "list": [
        {
          "quote": "Success is not final, failure is not fatal: It is the courage to continue that counts.",
          "author": "Winston Churchill"
        },
        {
          "quote": "The difference between a successful person and others is not a lack of strength, not a lack of knowledge, but rather a lack in will.",
          "author": "Vince Lombardi"
        },
        {
          "quote": "Perseverance is not a long race; it is many short races one after the other.",
          "author": "Walter Elliot"
        },
        {
          "quote": "It does not matter how slowly you go as long as you do not stop.",
          "author": "Confucius"
        },
        {
          "quote": "Success is stumbling from failure to failure with no loss of enthusiasm.",
          "author": "Winston Churchill"
        },
        {
          "quote": "The harder the conflict, the greater the triumph.",
          "author": "George Washington"
        },
        {
          "quote": "Perseverance, secret of all triumphs.",
          "author": "Victor Hugo"
        },
        {
          "quote": "Success is not the absence of failure; it's the persistence through failure.",
          "author": "Aisha Tyler"
        },
        {
          "quote": "It always seems impossible until it's done.",
          "author": "Nelson Mandela"
        },
        {
          "quote": "Perseverance is not giving up. It is persistence and tenacity, the effort required to do something and keep doing it till the end, even if it's hard.",
          "author": "Unknown"
        },
        {
          "quote": "The greatest glory in living lies not in never falling, but in rising every time we fall.",
          "author": "Nelson Mandela"
        },
        {
          "quote": "Perseverance is not a personality trait, it is an attitude we cultivate.",
          "author": "Unknown"
        },
        {
          "quote": "Fall seven times, stand up eight.",
          "author": "Japanese Proverb"
        },
        {
          "quote": "Perseverance is the hard work you do after you get tired of doing the hard work you already did.",
          "author": "Newt Gingrich"
        },
        {
          "quote": "The only way to fail is to stop trying.",
          "author": "Unknown"
        },
        {
          "quote": "Perseverance is not for the faint-hearted. It requires strength, determination, and a will to keep going no matter what.",
          "author": "Unknown"
        },
        {
          "quote": "I have not failed. I've just found 10,000 ways that won't work.",
          "author": "Thomas Edison"
        },
        {
          "quote": "Perseverance is the ability to keep going in spite of obstacles. It is the determination to achieve your goals no matter what challenges you face.",
          "author": "Unknown"
        },
        {
          "quote": "Don't watch the clock; do what it does. Keep going.",
          "author": "Sam Levenson"
        },
        {
          "quote": "Perseverance is not a one-time effort; it is a habit, a mindset, and a way of life.",
          "author": "Unknown"
        }
      ]
    },
    {
      "category": "Gratitude",
      "list": [
        {
          "quote": "Gratitude is the fairest blossom that springs from the soul.",
          "author": "Henry Ward Beecher"
        },
        {
          "quote": "Cultivate the habit of being grateful for every good thing that comes to you, and give thanks continuously.",
          "author": "Ralph Waldo Emerson"
        },
        {
          "quote": "Gratitude turns what we have into enough.",
          "author": "Anonymous"
        },
        {
          "quote": "Gratitude makes sense of our past, brings peace for today, and creates a vision for tomorrow.",
          "author": "Melody Beattie"
        },
        {
          "quote": "The more you practice gratitude, the more you see how much there is to be grateful for.",
          "author": "Unknown"
        },
        {
          "quote": "Gratitude is not only the greatest of virtues but the parent of all others.",
          "author": "Marcus Tullius Cicero"
        },
        {
          "quote": "Gratitude is the healthiest of all human emotions. The more you express gratitude for what you have, the more likely you will have even more to express gratitude for.",
          "author": "Zig Ziglar"
        },
        {
          "quote": "Gratitude unlocks the fullness of life. It turns what we have into enough, and more. It turns denial into acceptance, chaos to order, confusion to clarity. It can turn a meal into a feast, a house into a home, a stranger into a friend.",
          "author": "Melody Beattie"
        },
        {
          "quote": "Gratitude is a powerful catalyst for happiness. It's the spark that lights a fire of joy in your soul.",
          "author": "Amy Collette"
        },
        {
          "quote": "When you are grateful, fear disappears and abundance appears.",
          "author": "Anthony Robbins"
        },
        {
          "quote": "Gratitude is the wine for the soul. Go on. Get drunk.",
          "author": "Rumi"
        },
        {
          "quote": "Gratitude is not only the greatest of virtues but the parent of all others.",
          "author": "Marcus Tullius Cicero"
        },
        {
          "quote": "Gratitude is the healthiest of all human emotions. The more you express gratitude for what you have, the more likely you will have even more to express gratitude for.",
          "author": "Zig Ziglar"
        },
        {
          "quote": "Gratitude unlocks the fullness of life. It turns what we have into enough, and more. It turns denial into acceptance, chaos to order, confusion to clarity. It can turn a meal into a feast, a house into a home, a stranger into a friend.",
          "author": "Melody Beattie"
        },
        {
          "quote": "Gratitude is a powerful catalyst for happiness. It's the spark that lights a fire of joy in your soul.",
          "author": "Amy Collette"
        },
        {
          "quote": "When you are grateful, fear disappears and abundance appears.",
          "author": "Anthony Robbins"
        },
        {
          "quote": "Gratitude is the wine for the soul. Go on. Get drunk.",
          "author": "Rumi"
        },
        {
          "quote": "Gratitude makes sense of our past, brings peace for today, and creates a vision for tomorrow.",
          "author": "Melody Beattie"
        },
        {
          "quote": "The more you practice gratitude, the more you see how much there is to be grateful for.",
          "author": "Unknown"
        },
        {
          "quote": "Gratitude is the fairest blossom that springs from the soul.",
          "author": "Henry Ward Beecher"
        }
      ]
    },
    {
      "category": "Self Care",
      "list": [
        {
          "quote": "Self-care is not selfish. You cannot serve from an empty vessel.",
          "author": "Eleanor Brownn"
        },
        {
          "quote": "Caring for myself is not self-indulgence, it is self-preservation, and that is an act of political warfare.",
          "author": "Audre Lorde"
        },
        {
          "quote": "An empty lantern provides no light. Self-care is the fuel that allows your light to shine brightly.",
          "author": "Unknown"
        },
        {
          "quote": "Nourishing yourself in a way that helps you blossom in the direction you want to go is attainable, and you are worth the effort.",
          "author": "Deborah Day"
        },
        {
          "quote": "Rest and self-care are so important. When you take time to replenish your spirit, it allows you to serve others from the overflow. You cannot serve from an empty vessel.",
          "author": "Eleanor Brownn"
        },
        {
          "quote": "Self-care is giving the world the best of you instead of what's left of you.",
          "author": "Katie Reed"
        },
        {
          "quote": "Taking care of yourself doesn't mean me first, it means me too.",
          "author": "L.R. Knost"
        },
        {
          "quote": "Self-care is how you take your power back.",
          "author": "Lalah Delia"
        },
        {
          "quote": "The greatest wealth is health.",
          "author": "Virgil"
        },
        {
          "quote": "Taking care of yourself is part of taking care of others.",
          "author": "Unknown"
        },
        {
          "quote": "You can't pour from an empty cup. Take care of yourself first.",
          "author": "Unknown"
        },
        {
          "quote": "Self-care is not a luxury; it's a necessity.",
          "author": "Unknown"
        },
        {
          "quote": "When you take care of yourself, you're a better person for others. When you feel good about yourself, you treat others better.",
          "author": "Solange Knowles"
        },
        {
          "quote": "Self-care is the greatest gift you can give yourself and others.",
          "author": "Unknown"
        },
        {
          "quote": "Invest in yourself. You can afford it. Trust me.",
          "author": "Unknown"
        },
        {
          "quote": "Self-care is how you take your power back.",
          "author": "Lalah Delia"
        },
        {
          "quote": "Nourishing yourself in a way that helps you blossom in the direction you want to go is attainable, and you are worth the effort.",
          "author": "Deborah Day"
        },
        {
          "quote": "Rest and self-care are so important. When you take time to replenish your spirit, it allows you to serve others from the overflow. You cannot serve from an empty vessel.",
          "author": "Eleanor Brownn"
        },
        {
          "quote": "Self-care is giving the world the best of you instead of what's left of you.",
          "author": "Katie Reed"
        },
        {
          "quote": "Taking care of yourself doesn't mean me first, it means me too.",
          "author": "L.R. Knost"
        }
      ]
    },
    {
      "category": "Leadership",
      "list": [
        {
          "quote": "The function of leadership is to produce more leaders, not more followers.",
          "author": "Ralph Nader"
        },
        {
          "quote": "Leadership is not about being in charge. It is about taking care of those in your charge.",
          "author": "Simon Sinek"
        },
        {
          "quote": "A true leader has the confidence to stand alone, the courage to make tough decisions, and the compassion to listen to the needs of others.",
          "author": "Douglas MacArthur"
        },
        {
          "quote": "Leadership is the capacity to translate vision into reality.",
          "author": "Warren Bennis"
        },
        {
          "quote": "The greatest leader is not necessarily the one who does the greatest things. He is the one that gets the people to do the greatest things.",
          "author": "Ronald Reagan"
        },
        {
          "quote": "The function of leadership is to produce more leaders, not more followers.",
          "author": "Ralph Nader"
        },
        {
          "quote": "Leadership is not about being in charge. It is about taking care of those in your charge.",
          "author": "Simon Sinek"
        },
        {
          "quote": "A true leader has the confidence to stand alone, the courage to make tough decisions, and the compassion to listen to the needs of others.",
          "author": "Douglas MacArthur"
        },
        {
          "quote": "Leadership is the capacity to translate vision into reality.",
          "author": "Warren Bennis"
        },
        {
          "quote": "The greatest leader is not necessarily the one who does the greatest things. He is the one that gets the people to do the greatest things.",
          "author": "Ronald Reagan"
        },
        {
          "quote": "Leadership is not about being in charge. It is about taking care of those in your charge.",
          "author": "Simon Sinek"
        },
        {
          "quote": "A true leader has the confidence to stand alone, the courage to make tough decisions, and the compassion to listen to the needs of others.",
          "author": "Douglas MacArthur"
        },
        {
          "quote": "Leadership is the capacity to translate vision into reality.",
          "author": "Warren Bennis"
        },
        {
          "quote": "The greatest leader is not necessarily the one who does the greatest things. He is the one that gets the people to do the greatest things.",
          "author": "Ronald Reagan"
        },
        {
          "quote": "A leader is one who knows the way, goes the way, and shows the way.",
          "author": "John C. Maxwell"
        },
        {
          "quote": "Leadership is not about being in charge. It is about taking care of those in your charge.",
          "author": "Simon Sinek"
        },
        {
          "quote": "A true leader has the confidence to stand alone, the courage to make tough decisions, and the compassion to listen to the needs of others.",
          "author": "Douglas MacArthur"
        },
        {
          "quote": "Leadership is the capacity to translate vision into reality.",
          "author": "Warren Bennis"
        },
        {
          "quote": "The greatest leader is not necessarily the one who does the greatest things. He is the one that gets the people to do the greatest things.",
          "author": "Ronald Reagan"
        },
        {
          "quote": "A leader is one who knows the way, goes the way, and shows the way.",
          "author": "John C. Maxwell"
        }
      ]
    },
    {
      "category": "Friendship",
      "list": [
        {
          "quote": "Friendship is born at that moment when one person says to another, 'What! You too? I thought I was the only one.'",
          "author": "C.S. Lewis"
        },
        {
          "quote": "A true friend is someone who is always there for you, through the good times and the bad times.",
          "author": "Walter Winchell"
        },
        {
          "quote": "Friendship is the only cement that will ever hold the world together.",
          "author": "Woodrow Wilson"
        },
        {
          "quote": "A real friend is one who walks in when the rest of the world walks out.",
          "author": "Walter Winchell"
        },
        {
          "quote": "A true friend is someone who is always there for you, through the good times and the bad times.",
          "author": "Walter Winchell"
        },
        {
          "quote": "A friend is someone who knows all about you and still loves you.",
          "author": "Elbert Hubbard"
        },
        {
          "quote": "Friendship is the only cement that will ever hold the world together.",
          "author": "Woodrow Wilson"
        },
        {
          "quote": "A true friend is someone who is always there for you, through the good times and the bad times.",
          "author": "Walter Winchell"
        },
        {
          "quote": "A real friend is one who walks in when the rest of the world walks out.",
          "author": "Walter Winchell"
        },
        {
          "quote": "Friendship is born at that moment when one person says to another, 'What! You too? I thought I was the only one.'",
          "author": "C.S. Lewis"
        },
        {
          "quote": "A true friend is someone who is always there for you, through the good times and the bad times.",
          "author": "Walter Winchell"
        },
        {
          "quote": "Friendship is the only cement that will ever hold the world together.",
          "author": "Woodrow Wilson"
        },
        {
          "quote": "A real friend is one who walks in when the rest of the world walks out.",
          "author": "Walter Winchell"
        },
        {
          "quote": "A true friend is someone who is always there for you, through the good times and the bad times.",
          "author": "Walter Winchell"
        },
        {
          "quote": "A friend is someone who knows all about you and still loves you.",
          "author": "Elbert Hubbard"
        },
        {
          "quote": "Friendship is the only cement that will ever hold the world together.",
          "author": "Woodrow Wilson"
        },
        {
          "quote": "A true friend is someone who is always there for you, through the good times and the bad times.",
          "author": "Walter Winchell"
        },
        {
          "quote": "A real friend is one who walks in when the rest of the world walks out.",
          "author": "Walter Winchell"
        },
        {
          "quote": "Friendship is born at that moment when one person says to another, 'What! You too? I thought I was the only one.'",
          "author": "C.S. Lewis"
        },
        {
          "quote": "A true friend is someone who is always there for you, through the good times and the bad times.",
          "author": "Walter Winchell"
        }
      ]
    },
    {
      "category": "Time",
      "list": [
        {
          "quote": "The two most powerful warriors are patience and time.",
          "author": "Leo Tolstoy"
        },
        {
          "quote": "Time you enjoy wasting is not wasted time.",
          "author": "Marthe Troly-Curtin"
        },
        {
          "quote": "Lost time is never found again.",
          "author": "Benjamin Franklin"
        },
        {
          "quote": "Time is what we want most, but what we use worst.",
          "author": "William Penn"
        },
        {
          "quote": "Time flies over us, but leaves its shadow behind.",
          "author": "Nathaniel Hawthorne"
        },
        {
          "quote": "The best time to plant a tree was 20 years ago. The second best time is now.",
          "author": "Chinese Proverb"
        },
        {
          "quote": "Time is a created thing. To say 'I don't have time,' is like saying, 'I don't want to.'",
          "author": "Lao Tzu"
        },
        {
          "quote": "Time is the most valuable thing a man can spend.",
          "author": "Theophrastus"
        },
        {
          "quote": "Time is the wisest counselor of all.",
          "author": "Pericles"
        },
        {
          "quote": "Time is a great teacher, but unfortunately, it kills all its pupils.",
          "author": "Hector Berlioz"
        },
        {
          "quote": "Time is a gift that most of us take for granted.",
          "author": "Cher"
        },
        {
          "quote": "Time is the coin of your life. It is the only coin you have, and only you can determine how it will be spent. Be careful lest you let other people spend it for you.",
          "author": "Carl Sandburg"
        },
        {
          "quote": "Time is the longest distance between two places.",
          "author": "Tennessee Williams"
        },
        {
          "quote": "Time is more valuable than money. You can get more money, but you cannot get more time.",
          "author": "Jim Rohn"
        },
        {
          "quote": "The trouble is, you think you have time.",
          "author": "Buddha"
        },
        {
          "quote": "Time is what prevents everything from happening at once.",
          "author": "John Archibald Wheeler"
        },
        {
          "quote": "Time is the measurer of all things, but is itself immeasurable, and the grand discloser of all things, but is itself undisclosed.",
          "author": "Charles Caleb Colton"
        },
        {
          "quote": "You may delay, but time will not.",
          "author": "Benjamin Franklin"
        },
        {
          "quote": "Time is a dressmaker specializing in alterations.",
          "author": "Faith Baldwin"
        },
        {
          "quote": "Time slips away like grains of sand never to return again.",
          "author": "Robin Sharma"
        }
      ]
    },
    {
      "category": "Alone",
      "list": [
        {
          "quote": "It is better to be alone than in bad company.",
          "author": "George Washington"
        },
        {
          "quote": "The eternal quest of the human being is to shatter his loneliness.",
          "author": "Norman Cousins"
        },
        {
          "quote": "The greatest thing in the world is to know how to belong to oneself.",
          "author": "Michel de Montaigne"
        },
        {
          "quote": "The soul that sees beauty may sometimes walk alone.",
          "author": "Johann Wolfgang von Goethe"
        },
        {
          "quote": "When the people you love are gone, you're alone.",
          "author": "Keanu Reeves"
        },
        {
          "quote": "I restore myself when I'm alone.",
          "author": "Marilyn Monroe"
        },
        {
          "quote": "I think it's very healthy to spend time alone. You need to know how to be alone and not be defined by another person.",
          "author": "Oscar Wilde"
        },
        {
          "quote": "The greatest thing in the world is to know how to belong to oneself.",
          "author": "Michel de Montaigne"
        },
        {
          "quote": "The soul that sees beauty may sometimes walk alone.",
          "author": "Johann Wolfgang von Goethe"
        },
        {
          "quote": "When the people you love are gone, you're alone.",
          "author": "Keanu Reeves"
        },
        {
          "quote": "I restore myself when I'm alone.",
          "author": "Marilyn Monroe"
        },
        {
          "quote": "I think it's very healthy to spend time alone. You need to know how to be alone and not be defined by another person.",
          "author": "Oscar Wilde"
        },
        {
          "quote": "It is better to be alone than in bad company.",
          "author": "George Washington"
        },
        {
          "quote": "The eternal quest of the human being is to shatter his loneliness.",
          "author": "Norman Cousins"
        },
        {
          "quote": "The greatest thing in the world is to know how to belong to oneself.",
          "author": "Michel de Montaigne"
        },
        {
          "quote": "The soul that sees beauty may sometimes walk alone.",
          "author": "Johann Wolfgang von Goethe"
        },
        {
          "quote": "When the people you love are gone, you're alone.",
          "author": "Keanu Reeves"
        },
        {
          "quote": "I restore myself when I'm alone.",
          "author": "Marilyn Monroe"
        },
        {
          "quote": "I think it's very healthy to spend time alone. You need to know how to be alone and not be defined by another person.",
          "author": "Oscar Wilde"
        },
        {
          "quote": "It is better to be alone than in bad company.",
          "author": "George Washington"
        }
      ]
    },
    {
      "category": "Nature",
      "list": [
        {
          "quote": "In every walk with nature one receives far more than he seeks.",
          "author": "John Muir"
        },
        {
          "quote": "Look deep into nature, and then you will understand everything better.",
          "author": "Albert Einstein"
        },
        {
          "quote": "Nature always wears the colors of the spirit.",
          "author": "Ralph Waldo Emerson"
        },
        {
          "quote": "The poetry of the earth is never dead.",
          "author": "John Keats"
        },
        {
          "quote": "In nature, nothing is perfect and everything is perfect.",
          "author": "Alice Walker"
        },
        {
          "quote": "Nature does not hurry, yet everything is accomplished.",
          "author": "Lao Tzu"
        },
        {
          "quote": "The earth has music for those who listen.",
          "author": "William Shakespeare"
        },
        {
          "quote": "Nature is not a place to visit. It is home.",
          "author": "Gary Snyder"
        },
        {
          "quote": "Choose only one master—nature.",
          "author": "Rembrandt"
        },
        {
          "quote": "The clearest way into the universe is through a forest wilderness.",
          "author": "John Muir"
        },
        {
          "quote": "To me, a lush carpet of pine needles or spongy grass is more welcome than the most luxurious Persian rug.",
          "author": "Helen Keller"
        },
        {
          "quote": "Nature is pleased with simplicity. And nature is no dummy.",
          "author": "Isaac Newton"
        },
        {
          "quote": "Look deep into nature, and then you will understand everything better.",
          "author": "Albert Einstein"
        },
        {
          "quote": "Nature always wears the colors of the spirit.",
          "author": "Ralph Waldo Emerson"
        },
        {
          "quote": "The poetry of the earth is never dead.",
          "author": "John Keats"
        },
        {
          "quote": "In nature, nothing is perfect and everything is perfect.",
          "author": "Alice Walker"
        },
        {
          "quote": "Nature does not hurry, yet everything is accomplished.",
          "author": "Lao Tzu"
        },
        {
          "quote": "The earth has music for those who listen.",
          "author": "William Shakespeare"
        },
        {
          "quote": "Nature is not a place to visit. It is home.",
          "author": "Gary Snyder"
        },
        {
          "quote": "Choose only one master—nature.",
          "author": "Rembrandt"
        }
      ]
    },
    {
      "category": "Happiness",
      "list": [
        {
          "quote": "Happiness is not something ready-made. It comes from your own actions.",
          "author": "Dalai Lama"
        },
        {
          "quote": "The greatest happiness you can have is knowing that you do not necessarily require happiness.",
          "author": "William Saroyan"
        },
        {
          "quote": "Happiness is a direction, not a place.",
          "author": "Sydney J. Harris"
        },
        {
          "quote": "Happiness is the art of never holding in your mind the memory of any unpleasant thing that has passed.",
          "author": "Unknown"
        },
        {
          "quote": "Happiness is when what you think, what you say, and what you do are in harmony.",
          "author": "Mahatma Gandhi"
        },
        {
          "quote": "Happiness is a warm puppy.",
          "author": "Charles M. Schulz"
        },
        {
          "quote": "The happiness of your life depends upon the quality of your thoughts.",
          "author": "Marcus Aurelius"
        },
        {
          "quote": "The only joy in the world is to begin.",
          "author": "Cesare Pavese"
        },
        {
          "quote": "Happiness is not by chance, but by choice.",
          "author": "Jim Rohn"
        },
        {
          "quote": "The secret of happiness is freedom, and the secret of freedom is courage.",
          "author": "Thucydides"
        },
        {
          "quote": "The greater part of our happiness or misery depends upon our dispositions and not upon our circumstances.",
          "author": "Martha Washington"
        },
        {
          "quote": "Happiness is a state of mind. It's just according to the way you look at things.",
          "author": "Walt Disney"
        },
        {
          "quote": "Happiness is not a goal; it is a by-product.",
          "author": "Eleanor Roosevelt"
        },
        {
          "quote": "Happiness is when what you think, what you say, and what you do are in harmony.",
          "author": "Mahatma Gandhi"
        },
        {
          "quote": "Happiness is a warm puppy.",
          "author": "Charles M. Schulz"
        },
        {
          "quote": "The happiness of your life depends upon the quality of your thoughts.",
          "author": "Marcus Aurelius"
        },
        {
          "quote": "The only joy in the world is to begin.",
          "author": "Cesare Pavese"
        },
        {
          "quote": "Happiness is not by chance, but by choice.",
          "author": "Jim Rohn"
        },
        {
          "quote": "The secret of happiness is freedom, and the secret of freedom is courage.",
          "author": "Thucydides"
        },
        {
          "quote": "The greater part of our happiness or misery depends upon our dispositions and not upon our circumstances.",
          "author": "Martha Washington"
        }
      ]
    },
    {
      "category": "Women",
      "list": [
        {
          "quote": "A charming woman doesn't follow the crowd; she is herself.",
          "author": "Loretta Young"
        },
        {
          "quote": "The most alluring thing a woman can have is confidence.",
          "author": "Beyoncé"
        },
        {
          "quote": "Women are made to be loved, not understood.",
          "author": "Oscar Wilde"
        },
        {
          "quote": "A woman is like a tea bag; you never know how strong it is until it's in hot water.",
          "author": "Eleanor Roosevelt"
        },
        {
          "quote": "The best protection any woman can have is courage.",
          "author": "Elizabeth Cady Stanton"
        },
        {
          "quote": "Well-behaved women seldom make history.",
          "author": "Laurel Thatcher Ulrich"
        },
        {
          "quote": "The question isn't who's going to let me; it's who's going to stop me.",
          "author": "Ayn Rand"
        },
        {
          "quote": "A woman is the full circle. Within her is the power to create, nurture, and transform.",
          "author": "Diane Mariechild"
        },
        {
          "quote": "Women hold up half the sky.",
          "author": "Mao Zedong"
        },
        {
          "quote": "The empowered woman is powerful beyond measure and beautiful beyond description.",
          "author": "Steve Maraboli"
        },
        {
          "quote": "Women are the real architects of society.",
          "author": "Harriet Beecher Stowe"
        },
        {
          "quote": "Women are the largest untapped reservoir of talent in the world.",
          "author": "Hillary Clinton"
        },
        {
          "quote": "A strong woman looks a challenge in the eye and gives it a wink.",
          "author": "Gina Carey"
        },
        {
          "quote": "Women are the warriors of compassion.",
          "author": "Diane von Furstenberg"
        },
        {
          "quote": "A woman is like a tea bag; you never know how strong she is until she gets in hot water.",
          "author": "Eleanor Roosevelt"
        },
        {
          "quote": "The most alluring thing a woman can have is confidence.",
          "author": "Beyoncé"
        },
        {
          "quote": "A charming woman doesn't follow the crowd; she is herself.",
          "author": "Loretta Young"
        },
        {
          "quote": "Well-behaved women seldom make history.",
          "author": "Laurel Thatcher Ulrich"
        },
        {
          "quote": "The question isn't who's going to let me; it's who's going to stop me.",
          "author": "Ayn Rand"
        },
        {
          "quote": "A woman is the full circle. Within her is the power to create, nurture, and transform.",
          "author": "Diane Mariechild"
        }
      ]
    },
    {
      "category": "Men",
      "list": [
        {
          "quote": "A real man loves his wife, and places his family as the most important thing in life. Nothing has brought me more peace and contentment in life than simply being a good husband and father.",
          "author": "Frank Abagnale"
        },
        {
          "quote": "A man is not defined by his muscles, his facial hair, or his chromosomes. He is defined by his heart.",
          "author": "Unknown"
        },
        {
          "quote": "The measure of a man is what he does with power.",
          "author": "Plato"
        },
        {
          "quote": "Being male is a matter of birth. Being a man is a matter of age. But being a gentleman is a matter of choice.",
          "author": "Vin Diesel"
        },
        {
          "quote": "A man who dares to waste one hour of time has not discovered the value of life.",
          "author": "Charles Darwin"
        },
        {
          "quote": "The strength of a man isn't seen in the width of his shoulders. It's seen in the width of his arms that circle you.",
          "author": "Unknown"
        },
        {
          "quote": "A man's worth is no greater than his ambitions.",
          "author": "Marcus Aurelius"
        },
        {
          "quote": "The real man smiles in trouble, gathers strength from distress, and grows brave by reflection.",
          "author": "Thomas Paine"
        },
        {
          "quote": "A gentleman is one who puts more into the world than he takes out.",
          "author": "George Bernard Shaw"
        },
        {
          "quote": "The greatest glory in living lies not in never falling, but in rising every time we fall.",
          "author": "Nelson Mandela"
        },
        {
          "quote": "A real man provides, protects, and perseveres.",
          "author": "Unknown"
        },
        {
          "quote": "Being male is a matter of birth. Being a man is a matter of age. But being a gentleman is a matter of choice.",
          "author": "Vin Diesel"
        },
        {
          "quote": "The measure of a man is what he does with power.",
          "author": "Plato"
        },
        {
          "quote": "A man who dares to waste one hour of time has not discovered the value of life.",
          "author": "Charles Darwin"
        },
        {
          "quote": "Being male is a matter of birth. Being a man is a matter of age. But being a gentleman is a matter of choice.",
          "author": "Vin Diesel"
        },
        {
          "quote": "The measure of a man is what he does with power.",
          "author": "Plato"
        },
        {
          "quote": "A man who dares to waste one hour of time has not discovered the value of life.",
          "author": "Charles Darwin"
        },
        {
          "quote": "The strength of a man isn't seen in the width of his shoulders. It's seen in the width of his arms that circle you.",
          "author": "Unknown"
        },
        {
          "quote": "A man's worth is no greater than his ambitions.",
          "author": "Marcus Aurelius"
        },
        {
          "quote": "The real man smiles in trouble, gathers strength from distress, and grows brave by reflection.",
          "author": "Thomas Paine"
        }
      ]
    },
    {
      "category": "Family",
      "list": [
        {
          "quote": "Family is not an important thing, it's everything.",
          "author": "Michael J. Fox"
        },
        {
          "quote": "Rejoice with your family in the beautiful land of life.",
          "author": "Albert Einstein"
        },
        {
          "quote": "Family is the most important thing in the world.",
          "author": "Princess Diana"
        },
        {
          "quote": "In family life, love is the oil that eases friction, the cement that binds closer together, and the music that brings harmony.",
          "author": "Friedrich Nietzsche"
        },
        {
          "quote": "The family is one of nature's masterpieces.",
          "author": "George Santayana"
        },
        {
          "quote": "Family is not an important thing. It's everything.",
          "author": "Michael J. Fox"
        },
        {
          "quote": "A happy family is but an earlier heaven.",
          "author": "George Bernard Shaw"
        },
        {
          "quote": "Family means no one gets left behind or forgotten.",
          "author": "David Ogden Stiers"
        },
        {
          "quote": "The love in our family flows strong and deep, leaving us memories to treasure and keep.",
          "author": "Unknown"
        },
        {
          "quote": "Family is a gift that lasts forever.",
          "author": "Unknown"
        },
        {
          "quote": "Family is the heart of a home.",
          "author": "Unknown"
        },
        {
          "quote": "Family: where life begins and love never ends.",
          "author": "Unknown"
        },
        {
          "quote": "Family is the anchor that holds us through life's storms.",
          "author": "Unknown"
        },
        {
          "quote": "Family is the key to happiness.",
          "author": "Unknown"
        },
        {
          "quote": "Family is the compass that guides us.",
          "author": "Unknown"
        },
        {
          "quote": "Family is the light in the darkest moments.",
          "author": "Unknown"
        },
        {
          "quote": "Family is the place where hearts are always open.",
          "author": "Unknown"
        },
        {
          "quote": "Family is the tie that binds us together.",
          "author": "Unknown"
        },
        {
          "quote": "Family is the foundation of love and support.",
          "author": "Unknown"
        },
        {
          "quote": "Family is the source of strength and happiness.",
          "author": "Unknown"
        }
      ]
    }
  ],
  "wallpapers": [
    {
      "list": [
        "https://images.unsplash.com/photo-1623697899811-f2403f50685e?ixlib=rb-4.0.3&ixid=M3wxMjA3fDB8MHxzZWFyY2h8MTF8fGJsYW5rfGVufDB8fDB8fHww&auto=format&fit=crop&w=900&q=60",
        "https://images.unsplash.com/photo-1616441065120-81e9e146d3ef?ixlib=rb-4.0.3&ixid=M3wxMjA3fDB8MHxzZWFyY2h8OXx8Ymxhbmt8ZW58MHx8MHx8fDA%3D&auto=format&fit=crop&w=900&q=60",
        "https://images.unsplash.com/photo-1532276269954-64188308dcb3?ixlib=rb-4.0.3&ixid=M3wxMjA3fDB8MHxzZWFyY2h8NXx8Ymxhbmt8ZW58MHx8MHx8fDA%3D&auto=format&fit=crop&w=900&q=60",
        "https://images.unsplash.com/photo-1543378993-e0041dcb24cc?ixlib=rb-4.0.3&ixid=M3wxMjA3fDB8MHxzZWFyY2h8MTB8fGJsYW5rfGVufDB8fDB8fHww&auto=format&fit=crop&w=900&q=60",
        "https://images.unsplash.com/photo-1607827448287-456ca1b329d0?ixlib=rb-4.0.3&ixid=M3wxMjA3fDB8MHxzZWFyY2h8MTd8fGJsYW5rfGVufDB8fDB8fHww&auto=format&fit=crop&w=900&q=60",
        "https://images.unsplash.com/photo-1610790922811-cadc0a37d86c?ixlib=rb-4.0.3&ixid=M3wxMjA3fDB8MHxzZWFyY2h8MjB8fGJsYW5rfGVufDB8fDB8fHww&auto=format&fit=crop&w=900&q=60",
        "https://w0.peakpx.com/wallpaper/24/956/HD-wallpaper-dark-vertical-minimalism-artwork.jpg",
        "https://w0.peakpx.com/wallpaper/149/258/HD-wallpaper-dark-vertical-portrait-display.jpg",
        "https://wallpapercave.com/wp/wp9100291.jpg",
        "https://wallpaperaccess.com/full/1818293.jpg",
        "https://w0.peakpx.com/wallpaper/300/911/HD-wallpaper-dark-vertical-black.jpg",
        "https://wallpapercave.com/wp/wp4658073.jpg",
        "https://w0.peakpx.com/wallpaper/61/489/HD-wallpaper-leaves-plants-nature-dark-vertical-portrait-display-thumbnail.jpg",
        "https://images.unsplash.com/photo-1512850183-6d7990f42385?ixlib=rb-4.0.3&ixid=M3wxMjA3fDB8MHxzZWFyY2h8Mnx8ZGFyayUyMG1vZGUlMjB3YWxscGFwZXJ8ZW58MHx8MHx8fDA%3D&w=1000&q=80",
        "https://encrypted-tbn0.gstatic.com/images?q=tbn:ANd9GcQ3tAVP9EOoZw4T6nSkRipt9d_4mXVB7VfPpg&usqp=CAU",
        "https://encrypted-tbn0.gstatic.com/images?q=tbn:ANd9GcSrZTPE4PCtDZqN1q4lhYRcrZDKsieqjryQEw&usqp=CAU",
        "https://encrypted-tbn0.gstatic.com/images?q=tbn:ANd9GcSnq52OQHnSogCAdqYo_9eOXfXDdi7ReLjlYA&usqp=CAU",
        "https://r1.ilikewallpaper.net/iphone-wallpapers/download/5373/Black-3D-Blocks-iphone-wallpaper-ilikewallpaper_com_200.jpg",
        "https://encrypted-tbn0.gstatic.com/images?q=tbn:ANd9GcSr-vg5a2mNLJFNxdGipOMUO5tbal_zvEVstQ&usqp=CAU",
        "https://c4.wallpaperflare.com/wallpaper/459/436/979/branch-burning-campfire-dark-wallpaper-preview.jpg",
        "https://encrypted-tbn0.gstatic.com/images?q=tbn:ANd9GcTUk0I-hkcOgp_MHHL4rbzQ9PG5CZQjZmP9_g&usqp=CAU",
        "https://wallpaperaccess.com/full/1818293.jpg",
        "https://w0.peakpx.com/wallpaper/296/594/HD-wallpaper-forest-fog-dark-trees-gloom.jpg",
        "https://wallpapers.com/images/hd/dark-nature-rtq0dpbtouqf6xjb.jpg",
        "https://w0.peakpx.com/wallpaper/153/138/HD-wallpaper-dark-night-nature.jpg",
        "https://i.pinimg.com/736x/45/8d/ff/458dff40bbc74be34b6dbfc445fe5a50.jpg",
        "https://encrypted-tbn0.gstatic.com/images?q=tbn:ANd9GcSd9w60tMPcck90WZNlrlM2uUpTXqOGFJH1Jg&usqp=CAU"
      ]
    }
  ]
}
